apollo/__init__.py
apollo/apollo_client.py
apollo/python_2x.py
apollo/python_3x.py
apollo/util.py
apollo/jasypt/__init__.py
apollo/jasypt/decrypt.py
apollo/jasypt/encrypt.py
apollo/jasypt/utils.py
apollo/jasypt/zp_decrypt.py
demo/__init__.py
demo/demo.py
demo/demo_listener.py
demo/demo_secret.py
zpapollo-1.2.4.dist-info/METADATA
zpapollo-1.2.4.dist-info/WHEEL
zpapollo-1.2.4.dist-info/top_level.txt
zpapollo-1.2.4.dist-info/RECORD
