Metadata-Version: 2.1
Name: zpapollo
Version: 1.2.4
Summary: zpapollo
Home-page: https://github.com/
Author: zhidonglv
Author-email: 2907872121@qq.com
Platform: any
Classifier: Programming Language :: Python
Classifier: Programming Language :: Python :: 2.7
Classifier: Programming Language :: Python :: 3.6
Classifier: Programming Language :: Python :: 3.7
Classifier: Programming Language :: Python :: 3.8
Requires-Dist: requests
Requires-Dist: pycryptodome
